.gitignore
README
pyjsdoc.py
setup.py
PyJSDoc.egg-info/PKG-INFO
PyJSDoc.egg-info/SOURCES.txt
PyJSDoc.egg-info/dependency_links.txt
PyJSDoc.egg-info/entry_points.txt
PyJSDoc.egg-info/top_level.txt
PyJSDoc.egg-info/zip-safe
examples/class.js
examples/module.js
examples/module_closure.js
examples/subclass.js
static/__init__.py
static/jsdoc.css