Metadata-Version: 1.0
Name: PyJSDoc
Version: 0.9.0
Summary: Python port of JSDoc.
Home-page: http://jonathan.tang.name/code/pyjsdoc
Author: Jonathan Tang
Author-email: jonathan.d.tang@gmail.com
License: MIT License
Platform: Any
Classifier: Development Status :: 4 - Beta
Classifier: Intended Audience :: Developers
Classifier: License :: OSI Approved :: MIT License
Classifier: Programming Language :: Python
Classifier: Environment :: Console
Classifier: Topic :: Software Development :: Documentation
Classifier: Topic :: Internet :: WWW/HTTP
